[{"__type__":"cc.BitmapFont","_name":"fnt08","spriteFrame":{"__uuid__":"b0cmTArK9Bi6l1QbWwjQCy"},"fontSize":34,"_fntConfig":{"commonHeight":34,"fontSize":34,"atlasName":"fnt08.png","fontDefDictionary":{"48":{"rect":{"x":0,"y":0,"width":23,"height":34},"xOffset":0,"yOffset":0,"xAdvance":23},"49":{"rect":{"x":23,"y":0,"width":23,"height":34},"xOffset":0,"yOffset":0,"xAdvance":23},"50":{"rect":{"x":46,"y":0,"width":23,"height":34},"xOffset":0,"yOffset":0,"xAdvance":23},"51":{"rect":{"x":69,"y":0,"width":23,"height":34},"xOffset":0,"yOffset":0,"xAdvance":23},"52":{"rect":{"x":92,"y":0,"width":23,"height":34},"xOffset":0,"yOffset":0,"xAdvance":23},"53":{"rect":{"x":0,"y":34,"width":23,"height":34},"xOffset":0,"yOffset":0,"xAdvance":23},"54":{"rect":{"x":23,"y":34,"width":23,"height":34},"xOffset":0,"yOffset":0,"xAdvance":23},"55":{"rect":{"x":46,"y":34,"width":23,"height":34},"xOffset":0,"yOffset":0,"xAdvance":23},"56":{"rect":{"x":69,"y":34,"width":23,"height":34},"xOffset":0,"yOffset":0,"xAdvance":23},"57":{"rect":{"x":92,"y":34,"width":23,"height":34},"xOffset":0,"yOffset":0,"xAdvance":23}},"kerningDict":{}}},{"__type__":"cc.SpriteFrame","content":{"name":"fnt08","texture":"05rEh/7eNCWZUf9uxHWVbG","rect":[0,0,115,67],"offset":[0,0.5],"originalSize":[115,68],"capInsets":[0,0,0,0]}}]