[{"__type__":"cc.SpriteFrame","content":{"name":"mango_p6","texture":"a83Fji/LFBh74eMJYtofts","rect":[1368,632,140,140],"offset":[0,0],"originalSize":[140,140],"capInsets":[46,46,46,46]}},{"__type__":"cc.SpriteFrame","content":{"name":"default_btn_disabled","texture":"71VhFCTINJM6/Ky3oX9nBT","rect":[0,0,40,40],"offset":[0,0],"originalSize":[40,40],"capInsets":[12,12,12,12]}},{"__type__":"cc.SpriteFrame","content":{"name":"icon_rage_1","texture":"cc90WduuNL1Lwf+nMx7BTT","rect":[992,1250,20,27],"offset":[0,0],"originalSize":[20,27],"rotated":1,"capInsets":[0,0,0,0]}},{"__type__":"cc.SpriteFrame","content":{"name":"mango_pn_back_28","texture":"92xT2kOGBMTrzk5lu/9jCz","rect":[1092,52,442,142],"offset":[0,0],"originalSize":[442,142],"capInsets":[0,0,0,0]}},{"__type__":"cc.AnimationClip","_name":"show","_duration":0.15,"curveData":{"paths":{"Panel_mask":{"props":{"opacity":[{"frame":0.15,"value":191}]}},"NodeCenter":{"props":{"scaleX":[{"frame":0,"value":0.5},{"frame":0.1,"value":1.1},{"frame":0.15,"value":1}],"scaleY":[{"frame":0,"value":0.5},{"frame":0.1,"value":1.1},{"frame":0.15,"value":1}],"active":[{"frame":0,"value":true}],"opacity":[{"frame":0.15,"value":255}]}}}}},{"__type__":"cc.AnimationClip","_name":"hide","_duration":0.08333333333333333,"curveData":{"paths":{"Panel_mask":{"props":{"opacity":[{"frame":0,"value":191},{"frame":0.08333333333333333,"value":0}]}},"NodeCenter":{"props":{"scaleX":[{"frame":0,"value":1}],"scaleY":[{"frame":0,"value":1}],"active":[],"opacity":[{"frame":0,"value":255},{"frame":0.08333333333333333,"value":0}]}}}}},{"__type__":"cc.SpriteFrame","content":{"name":"fish_1jikuangbao","texture":"cc90WduuNL1Lwf+nMx7BTT","rect":[408,1256,110,110],"offset":[0,0],"originalSize":[110,110],"capInsets":[0,0,0,0]}},{"__type__":"cc.AnimationClip","_name":"lobby_personal_bag","_duration":0.25,"curveData":{"paths":{"Panel_mask":{"props":{"opacity":[{"frame":0,"value":0},{"frame":0.16666666666666666,"value":191},{"frame":0.25,"value":0}]}},"NodeCenter":{"props":{"scaleX":[{"frame":0.016666666666666666,"value":0.5},{"frame":0.11666666666666667,"value":1.1},{"frame":0.16666666666666666,"value":1}],"scaleY":[{"frame":0.016666666666666666,"value":0.5},{"frame":0.11666666666666667,"value":1.1},{"frame":0.16666666666666666,"value":1}],"active":[{"frame":0,"value":false},{"frame":0.016666666666666666,"value":true}],"opacity":[{"frame":0.16666666666666666,"value":255},{"frame":0.25,"value":0}]}}}}},[{"__type__":"cc.Prefab","_name":"lobby_personal_bag","data":{"__id__":1}},{"__type__":"cc.Node","_name":"lobby_personal_bag","_children":[{"__id__":2},{"__id__":4}],"_components":[{"__type__":"cc.Animation","node":{"__id__":1},"_clips":[{"__uuid__":"82coSVZdNIs5bUccUxamoY"},{"__uuid__":"3asWyZSSVAdKckljAiSJZ9"},{"__uuid__":"3baeH/IptHm7/UHXxAdgK+"}]}],"_prefab":{"__type__":"cc.PrefabInfo","root":{"__id__":1},"asset":{"__uuid__":"83LZTJYT1K6ZlczLEjr7yn"},"fileId":"c40/NehbNFT5tqBLr2Puvs"},"_contentSize":{"__type__":"cc.Size","width":1136,"height":640},"_anchorPoint":{"__type__":"cc.Vec2"},"_trs":{"__type__":"TypedArray","ctor":"Float64Array","array":[0,0,0,0,0,0,1,1,1,1]}},{"__type__":"cc.Node","_name":"Panel_mask","_parent":{"__id__":1},"_children":[{"__id__":3}],"_components":[{"__type__":"cc.BlockInputEvents","node":{"__id__":2}},{"__type__":"cc.StudioWidget","node":{"__id__":2},"_alignFlags":45,"_originalWidth":1136,"_originalHeight":640}],"_prefab":{"__type__":"cc.PrefabInfo","root":{"__id__":1},"asset":{"__uuid__":"83LZTJYT1K6ZlczLEjr7yn"},"fileId":"45eZ1QycROXq0/N4CD4LUe"},"_opacity":191,"_color":{"__type__":"cc.Color"},"_contentSize":{"__type__":"cc.Size","width":1136,"height":640},"_anchorPoint":{"__type__":"cc.Vec2"},"_trs":{"__type__":"TypedArray","ctor":"Float64Array","array":[0,0,0,0,0,0,1,1,1,1]}},{"__type__":"cc.Node","_name":"background","_parent":{"__id__":2},"_components":[{"__type__":"cc.Sprite","node":{"__id__":3},"_spriteFrame":{"__uuid__":"a2MjXRFdtLlYQ5ouAFv/+R"},"_sizeMode":0,"_isTrimmedMode":false},{"__type__":"cc.StudioWidget","node":{"__id__":3},"_alignFlags":45,"_originalWidth":1136,"_originalHeight":640}],"_prefab":{"__type__":"cc.PrefabInfo","root":{"__id__":1},"asset":{"__uuid__":"83LZTJYT1K6ZlczLEjr7yn"},"fileId":"c7Hn/lIXtNFpKASwK7JV6S"},"_color":{"__type__":"cc.Color"},"_contentSize":{"__type__":"cc.Size","width":1136,"height":640},"_trs":{"__type__":"TypedArray","ctor":"Float64Array","array":[568,320,0,0,0,0,1,1,1,1]}},{"__type__":"cc.Node","_name":"NodeCenter","_parent":{"__id__":1},"_children":[{"__id__":5},{"__id__":6},{"__id__":7},{"__id__":8},{"__id__":9},{"__id__":10},{"__id__":13},{"__id__":14},{"__type__":"cc.Node","_name":"btnNode","_parent":{"__id__":4},"_prefab":{"__type__":"cc.PrefabInfo","root":{"__id__":1},"asset":{"__uuid__":"83LZTJYT1K6ZlczLEjr7yn"},"fileId":"41+zunWfBNQa5/Em8jOgpx"},"_anchorPoint":{"__type__":"cc.Vec2"},"_trs":{"__type__":"TypedArray","ctor":"Float64Array","array":[177.8676,-157.6604,0,0,0,0,1,1,1,1]}},{"__id__":15},{"__id__":16}],"_components":[{"__type__":"cc.StudioWidget","node":{"__id__":4},"_alignFlags":12,"_left":0.5,"_bottom":0.5,"_isAbsLeft":false,"_isAbsBottom":false}],"_prefab":{"__type__":"cc.PrefabInfo","root":{"__id__":1},"asset":{"__uuid__":"83LZTJYT1K6ZlczLEjr7yn"},"fileId":"d8/+u+YHVKUYjCkJA1IUTV"},"_anchorPoint":{"__type__":"cc.Vec2"},"_trs":{"__type__":"TypedArray","ctor":"Float64Array","array":[568,320,0,0,0,0,1,1,1,1]}},{"__type__":"cc.Node","_name":"dikuang","_parent":{"__id__":4},"_components":[{"__type__":"cc.Sprite","node":{"__id__":5},"_spriteFrame":{"__uuid__":"a8kCfcyaVNZ4Ti3AmxmpyP"},"_type":1,"_sizeMode":0,"_isTrimmedMode":false}],"_prefab":{"__type__":"cc.PrefabInfo","root":{"__id__":1},"asset":{"__uuid__":"83LZTJYT1K6ZlczLEjr7yn"},"fileId":"5fwSsfYoNAgp9jYTdwFygF"},"_contentSize":{"__type__":"cc.Size","width":1058,"height":628},"_trs":{"__type__":"TypedArray","ctor":"Float64Array","array":[0,0,0,0,0,0,1,0.7,0.75,1]}},{"__type__":"cc.Node","_name":"Image_23","_parent":{"__id__":4},"_components":[{"__type__":"cc.Sprite","node":{"__id__":6},"_spriteFrame":{"__uuid__":"8eJWAuP89OGIdPWv7hd1f4"},"_type":1,"_sizeMode":0,"_isTrimmedMode":false}],"_prefab":{"__type__":"cc.PrefabInfo","root":{"__id__":1},"asset":{"__uuid__":"83LZTJYT1K6ZlczLEjr7yn"},"fileId":"20MadoDyhNYqZ+DS32IpsW"},"_contentSize":{"__type__":"cc.Size","width":280,"height":80},"_trs":{"__type__":"TypedArray","ctor":"Float64Array","array":[2.556,213.5031,0,0,0,0,1,0.7,0.7,1]}},{"__type__":"cc.Node","_name":"btnCloseBag","_parent":{"__id__":4},"_components":[{"__type__":"cc.BlockInputEvents","node":{"__id__":7}},{"__type__":"cc.Button","node":{"__id__":7},"zoomScale":1.1,"_N$transition":3,"transition":3,"_N$normalColor":{"__type__":"cc.Color","r":214,"g":214,"b":214},"_N$normalSprite":{"__uuid__":"ee62lb7jZKC6Sbv9O1QjHJ"},"_N$pressedSprite":{"__uuid__":"e97GVMl6JHh5Ml5qEDdSGa"},"pressedSprite":{"__uuid__":"e97GVMl6JHh5Ml5qEDdSGa"},"_N$hoverSprite":{"__uuid__":"ee62lb7jZKC6Sbv9O1QjHJ"},"hoverSprite":{"__uuid__":"ee62lb7jZKC6Sbv9O1QjHJ"},"_N$disabledSprite":{"__uuid__":"29FYIk+N1GYaeWH/q1NxQO"}},{"__type__":"cc.Sprite","node":{"__id__":7},"_spriteFrame":{"__uuid__":"ee62lb7jZKC6Sbv9O1QjHJ"},"_type":1,"_sizeMode":0,"_isTrimmedMode":false}],"_prefab":{"__type__":"cc.PrefabInfo","root":{"__id__":1},"asset":{"__uuid__":"83LZTJYT1K6ZlczLEjr7yn"},"fileId":"88a2sqVsJLV5BIbLjkRHaN"},"_contentSize":{"__type__":"cc.Size","width":90,"height":90},"_trs":{"__type__":"TypedArray","ctor":"Float64Array","array":[340.0051,186.6933,0,0,0,0,1,0.7,0.7,1]}},{"__type__":"cc.Node","_name":"Image_22","_parent":{"__id__":4},"_components":[{"__type__":"cc.Sprite","node":{"__id__":8},"_spriteFrame":{"__uuid__":"8c+Db6hSlNRa1J1YMqHcEo"},"_type":1,"_sizeMode":0,"_isTrimmedMode":false}],"_prefab":{"__type__":"cc.PrefabInfo","root":{"__id__":1},"asset":{"__uuid__":"83LZTJYT1K6ZlczLEjr7yn"},"fileId":"d9c6Bc/btC54HVk5iN2jIU"},"_contentSize":{"__type__":"cc.Size","width":314.2548,"height":348},"_anchorPoint":{"__type__":"cc.Vec2","x":1,"y":0.5},"_trs":{"__type__":"TypedArray","ctor":"Float64Array","array":[14.245,-25.6353,0,0,0,0,1,1,1,1]},"_eulerAngles":{"__type__":"cc.Vec3","z":-180}},{"__type__":"cc.Node","_name":"Image_13","_parent":{"__id__":4},"_components":[{"__type__":"cc.Sprite","node":{"__id__":9},"_spriteFrame":{"__uuid__":"34VDUaYZJOQ7dHkFTT7em0"},"_sizeMode":0,"_isTrimmedMode":false}],"_prefab":{"__type__":"cc.PrefabInfo","root":{"__id__":1},"asset":{"__uuid__":"83LZTJYT1K6ZlczLEjr7yn"},"fileId":"3136MILTBFN7snN0OKKzPQ"},"_contentSize":{"__type__":"cc.Size","width":328.7894,"height":57.092},"_trs":{"__type__":"TypedArray","ctor":"Float64Array","array":[183.0972,-127.362,0,0,0,0,1,1,1,1]}},{"__type__":"cc.Node","_name":"goodsSpBg","_parent":{"__id__":4},"_children":[{"__id__":11},{"__id__":12}],"_components":[{"__type__":"cc.Sprite","node":{"__id__":10},"_spriteFrame":{"__uuid__":"d2F8qwFOpI57U0MlUy5ipZ"},"_sizeMode":2,"_isTrimmedMode":false}],"_prefab":{"__type__":"cc.PrefabInfo","root":{"__id__":1},"asset":{"__uuid__":"83LZTJYT1K6ZlczLEjr7yn"},"fileId":"acYCmf/FNFVKjWfsaO8d+A"},"_contentSize":{"__type__":"cc.Size","width":120,"height":120},"_trs":{"__type__":"TypedArray","ctor":"Float64Array","array":[181.9514,78.7712,0,0,0,0,1,0.9,0.9,1]}},{"__type__":"cc.Node","_name":"goodsSp","_parent":{"__id__":10},"_components":[{"__type__":"cc.Sprite","node":{"__id__":11},"_spriteFrame":{"__uuid__":"5cJf8ca8NHC68XdTl55Mmc"},"_sizeMode":2,"_isTrimmedMode":false}],"_prefab":{"__type__":"cc.PrefabInfo","root":{"__id__":1},"asset":{"__uuid__":"83LZTJYT1K6ZlczLEjr7yn"},"fileId":"0fviuNsv1D8b8A3luRfa2h"},"_contentSize":{"__type__":"cc.Size","width":110,"height":110},"_trs":{"__type__":"TypedArray","ctor":"Float64Array","array":[-0.33080000000000354,-0.33310000000000173,0,0,0,0,1,0.94,0.94,1]}},{"__type__":"cc.Node","_name":"iconRage","_parent":{"__id__":10},"_active":false,"_components":[{"__type__":"cc.Sprite","node":{"__id__":12},"_spriteFrame":{"__uuid__":"30KIdziB9BdrfKTOHT70oh"},"_sizeMode":2,"_isTrimmedMode":false}],"_prefab":{"__type__":"cc.PrefabInfo","root":{"__id__":1},"asset":{"__uuid__":"83LZTJYT1K6ZlczLEjr7yn"},"fileId":"1e+VwZ689GfpHlR0BcL6cD"},"_contentSize":{"__type__":"cc.Size","width":20,"height":27},"_trs":{"__type__":"TypedArray","ctor":"Float64Array","array":[32.0001,32.0001,0,0,0,0,1,1,1,1]}},{"__type__":"cc.Node","_name":"bagSkillDes","_parent":{"__id__":4},"_components":[{"__type__":"cc.Label","node":{"__id__":13},"_useOriginalSize":false,"_string":"选择道具的描述，选择道具的\n描述选择道具的描述，\n选择道具的描述选择道具的\n择道具的描述择道具的描述","_N$string":"选择道具的描述，选择道具的\n描述选择道具的描述，\n选择道具的描述选择道具的\n择道具的描述择道具的描述","_fontSize":16,"_lineHeight":0,"_N$horizontalAlign":1,"_N$verticalAlign":1,"_N$overflow":1}],"_prefab":{"__type__":"cc.PrefabInfo","root":{"__id__":1},"asset":{"__uuid__":"83LZTJYT1K6ZlczLEjr7yn"},"fileId":"bd9Q20rNhIx7mW+P8ipd8E"},"_color":{"__type__":"cc.Color","r":199,"g":180,"b":255},"_contentSize":{"__type__":"cc.Size","width":258,"height":90},"_trs":{"__type__":"TypedArray","ctor":"Float64Array","array":[184.0654,-61.5905,0,0,0,0,1,1,1,1]}},{"__type__":"cc.Node","_name":"bagSkillName","_parent":{"__id__":4},"_components":[{"__type__":"cc.Label","node":{"__id__":14},"_string":"选择的道具名称","_N$string":"选择的道具名称","_fontSize":22,"_lineHeight":0}],"_prefab":{"__type__":"cc.PrefabInfo","root":{"__id__":1},"asset":{"__uuid__":"83LZTJYT1K6ZlczLEjr7yn"},"fileId":"19M7aDz5dBQ4h0ttk3gxm1"},"_contentSize":{"__type__":"cc.Size","width":154,"height":22},"_trs":{"__type__":"TypedArray","ctor":"Float64Array","array":[182.6272,3.1985,0,0,0,0,1,1,1,1]}},{"__type__":"cc.Node","_name":"Image_22_0","_parent":{"__id__":4},"_components":[{"__type__":"cc.Sprite","node":{"__id__":15},"_spriteFrame":{"__uuid__":"115sBcAo9IOqgu4E5gG/rE"},"_type":1,"_sizeMode":0,"_isTrimmedMode":false}],"_prefab":{"__type__":"cc.PrefabInfo","root":{"__id__":1},"asset":{"__uuid__":"83LZTJYT1K6ZlczLEjr7yn"},"fileId":"9cqmwkKypPAaGaL2drWssz"},"_contentSize":{"__type__":"cc.Size","width":320.7141,"height":348},"_trs":{"__type__":"TypedArray","ctor":"Float64Array","array":[-167.6646,-25.6352,0,0,0,0,1,1,1,1]}},{"__type__":"cc.Node","_name":"tableViewLayer","_parent":{"__id__":4},"_children":[{"__id__":17}],"_components":[{"__type__":"cc.BlockInputEvents","node":{"__id__":16}}],"_prefab":{"__type__":"cc.PrefabInfo","root":{"__id__":1},"asset":{"__uuid__":"83LZTJYT1K6ZlczLEjr7yn"},"fileId":"c3/Y0KEKpMaaUHoArONpcN"},"_contentSize":{"__type__":"cc.Size","width":314,"height":340},"_anchorPoint":{"__type__":"cc.Vec2"},"_trs":{"__type__":"TypedArray","ctor":"Float64Array","array":[-325.1463,-195.6339,0,0,0,0,1,1,1,1]}},{"__type__":"cc.Node","_name":"tableView","_parent":{"__id__":16},"_children":[{"__id__":18}],"_components":[{"__type__":"cc.ScrollView","node":{"__id__":17},"horizontal":false,"brake":0.75,"bounceDuration":0.23,"_N$content":{"__id__":19},"content":{"__id__":19},"_N$horizontalScrollBar":null,"_N$verticalScrollBar":null}],"_prefab":{"__type__":"cc.PrefabInfo","root":{"__id__":1},"asset":{"__uuid__":"83LZTJYT1K6ZlczLEjr7yn"},"fileId":"78k97jdhdHhZb55IP4GxLu"},"_contentSize":{"__type__":"cc.Size","width":314,"height":340},"_anchorPoint":{"__type__":"cc.Vec2"},"_trs":{"__type__":"TypedArray","ctor":"Float64Array","array":[0,0,0,0,0,0,1,1,1,1]}},{"__type__":"cc.Node","_name":"view","_parent":{"__id__":17},"_children":[{"__id__":19}],"_components":[{"__type__":"cc.Mask","node":{"__id__":18}}],"_prefab":{"__type__":"cc.PrefabInfo","root":{"__id__":1},"asset":{"__uuid__":"83LZTJYT1K6ZlczLEjr7yn"},"fileId":"99aUh4QNtJjZxTfIRPexyV"},"_contentSize":{"__type__":"cc.Size","width":314,"height":340},"_anchorPoint":{"__type__":"cc.Vec2"},"_trs":{"__type__":"TypedArray","ctor":"Float64Array","array":[0,0,0,0,0,0,1,1,1,1]}},{"__type__":"cc.Node","_name":"content","_parent":{"__id__":18},"_components":[{"__type__":"cc.Layout","node":{"__id__":19},"_resize":1,"_N$layoutType":2}],"_prefab":{"__type__":"cc.PrefabInfo","root":{"__id__":1},"asset":{"__uuid__":"83LZTJYT1K6ZlczLEjr7yn"},"fileId":"def8vMvxZG+5XKOMXaY3Xm"},"_contentSize":{"__type__":"cc.Size","width":314,"height":400},"_anchorPoint":{"__type__":"cc.Vec2","y":1},"_trs":{"__type__":"TypedArray","ctor":"Float64Array","array":[0,340,0,0,0,0,1,1,1,1]}}],{"__type__":"cc.SpriteFrame","content":{"name":"mango_pn_back_11","texture":"92xT2kOGBMTrzk5lu/9jCz","rect":[444,594,234,530],"offset":[0,0],"originalSize":[234,530],"capInsets":[11,11,11,11]}},{"__type__":"cc.SpriteFrame","content":{"name":"mango_af_sec_4","texture":"a83Fji/LFBh74eMJYtofts","rect":[1120,244,280,80],"offset":[0,0],"originalSize":[280,80],"capInsets":[60,26,60,26]}},{"__type__":"cc.SpriteFrame","content":{"name":"default_sprite_splash","texture":"02delMVqdBD70a/HSD99FK","rect":[0,0,2,2],"offset":[0,0],"originalSize":[2,2],"capInsets":[0,0,0,0]}},{"__type__":"cc.SpriteFrame","content":{"name":"mango_pn_back_10","texture":"92xT2kOGBMTrzk5lu/9jCz","rect":[678,594,1058,628],"offset":[0,0],"originalSize":[1058,628],"capInsets":[66,40,66,40]}},{"__type__":"cc.SpriteFrame","content":{"name":"fish_beibao_5","texture":"bbEmcwdtZFtLebWhtx+6Md","rect":[1156,512,120,120],"offset":[0,0],"originalSize":[120,120],"capInsets":[0,0,0,0]}},{"__type__":"cc.SpriteFrame","content":{"name":"default_btn_pressed","texture":"b4P/PCArtIdIH38t6mlw8Y","rect":[0,0,40,40],"offset":[0,0],"originalSize":[40,40],"capInsets":[12,12,12,12]}},{"__type__":"cc.SpriteFrame","content":{"name":"mango_btn_cm_6","texture":"a83Fji/LFBh74eMJYtofts","rect":[950,412,90,90],"offset":[0,0],"originalSize":[90,90],"capInsets":[15,11,15,11]}}]