[{"__type__":"cc.SpriteFrame","content":{"name":"fish_xinpaotaitishi","texture":"bbEmcwdtZFtLebWhtx+6Md","rect":[1174,47,56,34],"offset":[0,0],"originalSize":[56,34],"capInsets":[5,14,5,14]}},[{"__type__":"cc.Prefab","_name":"message_tip_label","data":{"__id__":1}},{"__type__":"cc.Node","_name":"Node","_children":[{"__id__":2}],"_prefab":{"__type__":"cc.PrefabInfo","root":{"__id__":1},"asset":{"__id__":0},"fileId":"41CLke91lE5Kj7APpFe/dg"},"_trs":{"__type__":"TypedArray","ctor":"Float64Array","array":[0,0,0,0,0,0,1,1,1,1]}},{"__type__":"cc.Node","_name":"archor","_parent":{"__id__":1},"_children":[{"__id__":3},{"__id__":4}],"_prefab":{"__type__":"cc.PrefabInfo","root":{"__id__":1},"asset":{"__id__":0},"fileId":"d8725KZZpMoqOmqlirq3gj"},"_anchorPoint":{"__type__":"cc.Vec2"},"_trs":{"__type__":"TypedArray","ctor":"Float64Array","array":[0,0,0,0,0,0,1,1,1,1]}},{"__type__":"cc.Node","_name":"tip_bg","_parent":{"__id__":2},"_components":[{"__type__":"cc.Sprite","node":{"__id__":3},"_spriteFrame":{"__uuid__":"7dCfvYc5VI2Jr2Q2+pIYuk"},"_type":1,"_sizeMode":0,"_isTrimmedMode":false}],"_prefab":{"__type__":"cc.PrefabInfo","root":{"__id__":1},"asset":{"__id__":0},"fileId":"65FRdjGlROUYKQfr7rB82P"},"_contentSize":{"__type__":"cc.Size","width":400,"height":34},"_trs":{"__type__":"TypedArray","ctor":"Float64Array","array":[0,0,0,0,0,0,1,1,1,1]}},{"__type__":"cc.Node","_name":"txt","_parent":{"__id__":2},"_components":[{"__type__":"cc.Label","node":{"__id__":4},"_string":"春江潮水连海平","_N$string":"春江潮水连海平","_fontSize":20,"_lineHeight":0}],"_prefab":{"__type__":"cc.PrefabInfo","root":{"__id__":1},"asset":{"__id__":0},"fileId":"bdJPqz4sdALIIfHbKmPX5m"},"_contentSize":{"__type__":"cc.Size","width":140,"height":20},"_trs":{"__type__":"TypedArray","ctor":"Float64Array","array":[0,0,0,0,0,0,1,1,1,1]}}]]